thread_safe_sqlite/__init__.py
thread_safe_sqlite/query.py
thread_safe_sqlite/result.py
thread_safe_sqlite/schema.py
thread_safe_sqlite/sqlite3worker.py
thread_safe_sqlite/store.py
thread_safe_sqlite-0.0.1.dist-info/LICENSE.txt
thread_safe_sqlite-0.0.1.dist-info/METADATA
thread_safe_sqlite-0.0.1.dist-info/WHEEL
thread_safe_sqlite-0.0.1.dist-info/top_level.txt
thread_safe_sqlite-0.0.1.dist-info/RECORD
